utilities_pufm/.gitignore
utilities_pufm/__init__.py
utilities_pufm/csvs/csvs.py
utilities_pufm/database/__init__.py
utilities_pufm/database/db_connection/__init__.py
utilities_pufm/database/db_connection/mysql_connection.py
utilities_pufm/database/db_connection/pg_connection.py
utilities_pufm/database/enums.py
utilities_pufm/database/factories/__init__.py
utilities_pufm/database/factories/connection_factory.py
utilities_pufm/database/utils_db/__init__.py
utilities_pufm/database/utils_db/mysql_runner.py
utilities_pufm/database/utils_db/postgres_runner.py
utilities_pufm/database/utils_db/utils_sql.py
utilities_pufm/dataframe/df.py
utilities_pufm/enums/enums.py
utilities_pufm/exceptions/exception.py
utilities_pufm/files/files.py
utilities_pufm/git/__init__.py
utilities_pufm/git/git_script_manager.py
utilities_pufm/git/scripts/limpar_git_ignored.sh
utilities_pufm/git/scripts/remove_ignored_from_git.sh
utilities_pufm/git_manager/__init__.py
utilities_pufm/git_manager/git.py
utilities_pufm/jsons/__init__.py
utilities_pufm/jsons/jsons.py
utilities_pufm/paths/__init__.py
utilities_pufm/paths/directories.py
utilities_pufm/paths/paths.py
utilities_pufm/prints/logs.py
utilities_pufm/prints/prints.py
utilities_pufm/prints/rich.py
utilities_pufm/reports/reports.py
utilities_pufm/reports/wkhtmltopdf.exe
utilities_pufm/security/__init__.py
utilities_pufm/security/hashs.py
utilities_pufm/strings/strings.py
utilities_pufm/teste.py
utilities_pufm/time/time.py
utilities_pufm/utils/__init__.py
utilities_pufm/utils/enums.py
utilities_pufm/utils/question.py
utilities_pufm-0.1.1.dist-info/LICENSE
utilities_pufm-0.1.1.dist-info/METADATA
utilities_pufm-0.1.1.dist-info/WHEEL
utilities_pufm-0.1.1.dist-info/RECORD
