Metadata-Version: 2.3
Name: utilities_pufm
Version: 0.1.1
Summary: Utilities Packages
Author: Lucas Batista
Author-email: lucas.daniel.bp@gmail.com
Requires-Python: >=3.10,<3.14
Classifier: Programming Language :: Python :: 3
Classifier: Programming Language :: Python :: 3.10
Classifier: Programming Language :: Python :: 3.11
Classifier: Programming Language :: Python :: 3.12
Classifier: Programming Language :: Python :: 3.13
Requires-Dist: pandas (>=2.2.3,<3.0.0)
Requires-Dist: rich (>=14.0.0,<15.0.0)
Requires-Dist: sqlalchemy (>=2.0.40,<3.0.0)
